[{"name":"남*철 ","date":"2019.06.10","rating":"2","text":"\n                    \n                        370mm 핸들에 잘 들어갑니다.재질의 접촉느낌은 나쁘지 않지만 생각보다 두껍습니다. 물론 핸들커버가 가지는 문제입니다. 큰 문제는 냄새입니다. 배송 후 실외에 방치했지만, 냄새가 아직 심합니다. 운전 후 손에도 냄새가.... TVOC가 나오는 거는 아닌지 잘 모르겠네요. 냄새는 제품마다 다를거라 생각하지 않습니다. 제조사에서 냄새 제거 후 판매했으면 합니다. 시간이 흐른 후에도 냄새가 나는지 확인해봐야겠네요. 장착사진은 따로 올리지 않습니다. 장착 후 별다른 외관문제는 없습니다.\n                    \n                "},{"name":"돌싱 ","date":"2019.03.18","rating":"2","text":"\n                    \n                        장착했는데 사진처럼 한쪽부분이 우네요.. 혹시나 싶어서 뒤집어서 끼워도 똑같이 우네요.. 보이는 부분 보단 뒷부분이 보기가 나아서 우는부분이 뒤로가게 해서 장착해 사용하는데 다음 부턴 신경 써서 만들어주시길 부탁드립니다.\n확실히 열선 반응은 많이 느리네요..\n\n그리고 끼울때 그렇게 빡시다는 생각을 못했는데 끼우기 빡시다는분들은 핸들사이즈 380 인데 370 구매하신거 아닌가요?\n                    \n                "},{"name":"정*규 ","date":"2019.04.19","rating":"2","text":"\n                    \n                        포장이 너무 단촐하네요.  핸들커버만 달랑 포장지안에 들어있네요.  벌크제품인가. 덕분에 분리수거할거 없어서 ㅋㅋ.\n근데 냄새가 너무 납니다. 차에 설치할때는 작아서 겨우 끼웠고 며칠동안 운전할때 냄새로 머리가 아프고 손에 냄새가 베일정도내요.\n                    \n                "},{"name":"이*미 ","date":"2020.09.27","rating":"2","text":"\n                    \n                        쿠팡문제인지  만드는 제품 회사 문제인지?\n혹시나 커버 안 뒤집어서  봤는데  파리한마리  구더기한마리  각가 시체나옴\n\n 쿠팡서  보관을 ㅈ같이  한건지   케이멤 모터스가 ㅈ같이 만든건지?으으으으으\n                    \n                "},{"name":"송*수 ","date":"2019.04.08","rating":"2","text":"\n                    \n                        핸들의 그립감은 좋은데...\n도무지 냄새가 없어지지가 않네요  \n개봉하고 이틀정도 사용후 냄새가 심하고 손에도 묻어나와 베란다 햇빛 잘 드는 곳에 일주일을 방치해보고 다시 사용중인데.. 제거가 안되네요 \n냄새땜에 ng입니다\n                    \n                "},{"name":"이*희 ","date":"2019.09.16","rating":"2","text":"\n                    \n                        제품에서 플라스틱냄새?? 화학제품냄새?? 아무튼 재질에서 나는 냄새같은데 엄청납니다, 예민하신분들은 머리좀 아플듯... 정말 딱 돈값만큼만하는 것같아요 \n다시 살래?? 라고 물으면 그냥 좀 더주고 다른거 살께요 할듯\n                    \n                "},{"name":"라*영 ","date":"2020.08.17","rating":"2","text":"\n                    \n                        만원 초반 대 구하다가 그냥 2만원까지 쓰자 해서 삿는디\n만원 초반대랑 퀄이 같음 ㅋ\n뭐... 암튼 그립감도 보통이고 그래요 ㅎ....\n                    \n                "},{"name":"구매in ","date":"2018.12.04","rating":"2","text":"\n                    \n                        냄새엄청심하네요  열선핸들커버로산건데  전혀안따듯해서  깜짝놀라서  떼어내고   원래부착했던거  다시했어요  돈버렸네요\n                    \n                "},{"name":"이*혁 ","date":"2020.05.24","rating":"2","text":"\n                    \n                        손이안미끄러지는제품을원했는데그렇지가않네요\n                    \n                "},{"name":"허*복 ","date":"2021.06.10","rating":"2","text":"\n                    \n                        도대체 원산지가 한국인가요 차이나인가요  ㅡ.ㅡ.\n                    \n                "},{"name":"송*희 ","date":"2020.01.11","rating":"2","text":""},{"name":"윤*진 ","date":"2019.11.13","rating":"2","text":""},{"name":"탈*원 ","date":"2019.03.20","rating":"2","text":""},{"name":"탁*순 ","date":"2019.04.25","rating":"2","text":"\n                    \n                        냄새가 많이나요\n                    \n                "},{"name":"이*근 ","date":"2019.09.26","rating":"2","text":"\n                    \n                        색상이 때탄거같은 느낌입니다\n                    \n                "},{"name":"장*모 ","date":"2019.11.25","rating":"2","text":"\n                    \n                        너무 차거워요.. 가격대비 싼티나요\n                    \n                "},{"name":"장*열 ","date":"2019.10.05","rating":"2","text":"\n                    \n                        냄새가 아직도 좀 나지만 그래도 쓸만\n                    \n                "},{"name":"이*은 ","date":"2019.02.07","rating":"2","text":"\n                    \n                        공기반이 아니구 공기가 95%\n너무 심하다~~~\n과대포장\n                    \n                "},{"name":"j*i ","date":"2020.06.30","rating":"2","text":""},{"name":"P*I ","date":"2020.02.16","rating":"2","text":""},{"name":"김*수 ","date":"2019.05.29","rating":"2","text":""},{"name":"김*욱 ","date":"2021.04.17","rating":"2","text":""},{"name":"고*영 ","date":"2021.05.16","rating":"2","text":""},{"name":"D*A ","date":"2021.06.16","rating":"2","text":""},{"name":"배*우 ","date":"2021.06.27","rating":"2","text":""},{"name":"이*선 ","date":"2021.06.27","rating":"2","text":""},{"name":"선*은 ","date":"2021.06.30","rating":"2","text":""}]